artless_template.py
artless_template-0.6.3.dist-info/licenses/LICENSE
artless_template-0.6.3.dist-info/METADATA
artless_template-0.6.3.dist-info/WHEEL
artless_template-0.6.3.dist-info/top_level.txt
artless_template-0.6.3.dist-info/RECORD
