Metadata-Version: 2.4
Name: artless-template
Version: 0.6.3
Summary: The artless and minimalist templating for Python server-side rendering.
Author-email: Peter Bro <p3t3rbr0@gmail.com>
License-Expression: MIT
Project-URL: Homepage, https://git.peterbro.su/peter/py3-artless-template
Project-URL: Repository, https://git.peterbro.su/peter/py3-artless-template.git
Project-URL: Issues, https://git.peterbro.su/peter/py3-artless-template/issues
Project-URL: Documentation, https://pages.peterbro.su/py3-artless-template/
Project-URL: Changelog, https://pages.peterbro.su/py3-pure-template/changelog.html
Keywords: artless-template,template engine,text processing,utility
Classifier: Development Status :: 4 - Beta
Classifier: Intended Audience :: Developers
Classifier: Operating System :: OS Independent
Classifier: Programming Language :: Python :: 3
Classifier: Programming Language :: Python :: 3.11
Classifier: Programming Language :: Python :: 3.12
Classifier: Programming Language :: Python :: 3.13
Classifier: Topic :: Text Processing :: Markup
Classifier: Topic :: Text Processing :: Markup :: HTML
Classifier: Topic :: Software Development
Classifier: Topic :: Software Development :: Libraries
Classifier: Topic :: Software Development :: Libraries :: Python Modules
Classifier: Typing :: Typed
Requires-Python: >=3.11
License-File: LICENSE
Provides-Extra: build
Requires-Dist: build==1.2.2.post1; extra == "build"
Requires-Dist: twine==6.1.0; extra == "build"
Provides-Extra: docs
Requires-Dist: Sphinx==8.2.3; extra == "docs"
Requires-Dist: furo==2025.7.19; extra == "docs"
Provides-Extra: dev
Requires-Dist: coverage==7.10.1; extra == "dev"
Requires-Dist: mypy==1.17.0; extra == "dev"
Requires-Dist: isort==6.0.1; extra == "dev"
Requires-Dist: flake8==7.3.0; extra == "dev"
Requires-Dist: black==25.1.0; extra == "dev"
Provides-Extra: benchmarks
Requires-Dist: Django==5.2.4; extra == "benchmarks"
Requires-Dist: Jinja2==3.1.6; extra == "benchmarks"
Requires-Dist: Mako==1.3.10; extra == "benchmarks"
Requires-Dist: python-fasthtml==0.12.22; extra == "benchmarks"
Dynamic: license-file
